{
  "name": "projects/proto-2024/stl/SN-603-04_1771247301922.stl",
  "bucket": "demo-bom3d-sn923.appspot.com",
  "metageneration": 1,
  "generation": 1771247301955,
  "contentType": "application/octet-stream",
  "storageClass": "STANDARD",
  "contentDisposition": "inline",
  "downloadTokens": [
    "1bd0e791-60b5-440c-926c-31f92b54c051"
  ],
  "etag": "/x9iN7xhXS48hRbzowD5MAEXtUg",
  "customMetadata": {},
  "timeCreated": "2026-02-16T13:08:21.955Z",
  "updated": "2026-02-16T13:08:21.955Z",
  "size": 154284,
  "md5Hash": "nxTXpaU4zzZcHBuNFtWBCg==",
  "crc32c": "2039807248"
}